openatlas/__init__.py
openatlas/agent.py
openatlas/cli.py
openatlas/julia_browser_tools.py
openatlas-1.0.7.dist-info/licenses/LICENSE
openatlas-1.0.7.dist-info/METADATA
openatlas-1.0.7.dist-info/WHEEL
openatlas-1.0.7.dist-info/entry_points.txt
openatlas-1.0.7.dist-info/top_level.txt
openatlas-1.0.7.dist-info/RECORD
