Metadata-Version: 2.4
Name: openatlas
Version: 1.0.7
Summary: An autonomous browser agent with web search and interactive browsing capabilities
Home-page: https://github.com/openatlas/openatlas
Author: Harish Santhanalakshmi Ganesan
Author-email: 
License: MIT
Project-URL: Homepage, https://github.com/openatlas/openatlas
Project-URL: Bug Reports, https://github.com/openatlas/openatlas/issues
Project-URL: Source, https://github.com/openatlas/openatlas
Keywords: ai,agent,browser,automation,web-scraping,llm,claude,gpt,gemini
Classifier: Development Status :: 4 - Beta
Classifier: Intended Audience :: Developers
Classifier: Topic :: Software Development :: Libraries :: Application Frameworks
Classifier: License :: OSI Approved :: MIT License
Classifier: Programming Language :: Python :: 3
Classifier: Programming Language :: Python :: 3.11
Classifier: Programming Language :: Python :: 3.12
Requires-Python: >=3.11
License-File: LICENSE
Requires-Dist: agno
Requires-Dist: ddgs
Requires-Dist: httpx
Requires-Dist: julia_browser
Requires-Dist: python-dotenv
Requires-Dist: anthropic
Requires-Dist: litellm
Requires-Dist: openai
Requires-Dist: google-genai
Requires-Dist: sqlalchemy
Dynamic: home-page
Dynamic: license-file
Dynamic: requires-python
